MANIFEST.in
README.rst
setup.cfg
setup.py
pipwrap/__init__.py
pipwrap/cli.py
pipwrap/command.py
pipwrap.egg-info/PKG-INFO
pipwrap.egg-info/SOURCES.txt
pipwrap.egg-info/dependency_links.txt
pipwrap.egg-info/entry_points.txt
pipwrap.egg-info/requires.txt
pipwrap.egg-info/top_level.txt
requirements/package.txt
test/test_cli.py
test/test_command.py