Metadata-Version: 1.1
Name: pipwrap
Version: 0.2.1
Summary: Manages pip requirements files for multiple environments, e.g. production and development
Home-page: https://github.com/jessamynsmith/pipwrap
Author: Jessamyn Smith
Author-email: jessamyn.smith@gmail.com
License: MIT
Download-URL: https://github.com/jessamynsmith/pipwrap/archive/v0.2.1.tar.gz
Keywords: pip,upgrade,requirements,heroku,development,production
Platform: UNKNOWN
Classifier: Development Status :: 4 - Beta
Classifier: Environment :: Console
Classifier: Intended Audience :: Developers
Classifier: Programming Language :: Python
Classifier: Programming Language :: Python :: 2.7
Classifier: Programming Language :: Python :: 3.2
Classifier: Programming Language :: Python :: 3.3
Classifier: Programming Language :: Python :: 3.4
Classifier: License :: OSI Approved :: MIT License
Classifier: Topic :: Software Development
Classifier: Topic :: Utilities
